Metadata-Version: 1.1
Name: electrum-client
Version: 0.0.1
Summary: A minimal client library for Electrum.
Home-page: https://github.com/tylerchambers/electrum-client
Author: Tyler Chambers
Author-email: me@tylerchambers.net
License: MIT License
